contact_persons_local/__init__.py
contact_persons_local/contact_persons_local.py
contact_persons_local/contact_persons_local_constants.py
contact_persons_local-0.0.24.dist-info/METADATA
contact_persons_local-0.0.24.dist-info/WHEEL
contact_persons_local-0.0.24.dist-info/top_level.txt
contact_persons_local-0.0.24.dist-info/RECORD
