Metadata-Version: 2.1
Name: contact-persons-local
Version: 0.0.24
Summary: PyPI Package for Circles contact-person-local Python
Home-page: https://github.com/circles-zone/contact-persons-local-python-package
Author: Circles
Author-email: info@circlez.ai
Classifier: Programming Language :: Python :: 3
Classifier: License :: Other/Proprietary License
Classifier: Operating System :: OS Independent
Requires-Dist: database-mysql-local >=0.0.290
Requires-Dist: logger-local >=0.0.135
Requires-Dist: person-local >=0.0.52
Requires-Dist: contact-local
